maliang/__init__.py
maliang/animation/__init__.py
maliang/animation/animations.py
maliang/animation/controllers.py
maliang/color/__init__.py
maliang/color/colortable.py
maliang/color/convert.py
maliang/color/hsl.py
maliang/color/rgb.py
maliang/core/__init__.py
maliang/core/configs.py
maliang/core/containers.py
maliang/core/virtual.py
maliang/standard/__init__.py
maliang/standard/dialogs.py
maliang/standard/features.py
maliang/standard/images.py
maliang/standard/shapes.py
maliang/standard/styles.py
maliang/standard/texts.py
maliang/standard/widgets.py
maliang/theme/__init__.py
maliang/theme/manager.py
maliang/toolbox/__init__.py
maliang/toolbox/enhanced.py
maliang/toolbox/utility.py
maliang-3.1.5.dist-info/licenses/LICENSE.txt
maliang-3.1.5.dist-info/METADATA
maliang-3.1.5.dist-info/WHEEL
maliang-3.1.5.dist-info/top_level.txt
maliang-3.1.5.dist-info/RECORD
