Metadata-Version: 2.4
Name: maliang
Version: 3.1.5
Summary: A lightweight UI framework based on tkinter with all UI drawn in Canvas.
Author: Xiaokang2022
Author-email: 2951256653@qq.com
Maintainer: Xiaokang2022
Maintainer-email: 2951256653@qq.com
License: MIT
Project-URL: Bug tracker, https://github.com/Xiaokang2022/maliang/issues
Project-URL: Changelog, https://xiaokang2022.github.io/maliang/CHANGELOG/
Project-URL: Documentation, https://xiaokang2022.github.io/maliang-docs/
Project-URL: Donate, https://xiaokang2022.github.io/maliang/Sponsor/
Project-URL: Homepage, https://xiaokang2022.github.io/maliang/
Project-URL: Source code, https://github.com/Xiaokang2022/maliang
Keywords: tkinter,gui,ui,cross-platform,themed,typed,lightweight,ui-design,modern-ui,custom
Classifier: Programming Language :: Python :: 3
Classifier: License :: OSI Approved :: MIT License
Classifier: Operating System :: Microsoft :: Windows
Classifier: Operating System :: POSIX :: Linux
Classifier: Operating System :: MacOS
Classifier: Intended Audience :: Developers
Classifier: Typing :: Typed
Requires-Python: >=3.10
License-File: LICENSE.txt
Requires-Dist: typing-extensions
Provides-Extra: opt
Requires-Dist: darkdetect==0.8.0; extra == "opt"
Requires-Dist: darkdetect[macos-listener]==0.8.0; platform_system == "Darwin" and extra == "opt"
Requires-Dist: pywinstyles==1.8; platform_system == "Windows" and extra == "opt"
Requires-Dist: hPyT==1.4.0; platform_system == "Windows" and extra == "opt"
Requires-Dist: win32material==1.0.7; platform_system == "Windows" and extra == "opt"
Requires-Dist: pillow>=10.0.0; extra == "opt"
Provides-Extra: ext
Requires-Dist: maliang-mpl>=1.2.3; extra == "ext"
Requires-Dist: maliang-media>=1.1.3; extra == "ext"
Requires-Dist: maliang-three>=1.0.3; extra == "ext"
Requires-Dist: maliang-table; extra == "ext"
Dynamic: license-file
